{
  "headers": {
    "x-content-type-options": "nosniff",
    "last-modified": "Fri, 25 Mar 2022 13:32:50 GMT",
    "x-amz-cf-id": "vnYKiJBGszkW2K4wOA5KXOKtJiuk8gL-dg2DbiL5Xp33LpNYCe-Msw==",
    "cross-origin-embedder-policy": "same-origin",
    "x-amz-replication-status": "COMPLETED",
    "server": "deno/gcp-europe-west3",
    "etag": "\"63c5c93a70af8e2997bc127df94b101d\"",
    "accept-ranges": "bytes",
    "date": "Fri, 29 Dec 2023 23:20:51 GMT",
    "strict-transport-security": "max-age=63072000; includeSubDomains; preload",
    "cross-origin-resource-policy": "same-origin",
    "x-amz-cf-pop": "FRA56-P5",
    "x-cache": "Hit from cloudfront",
    "access-control-allow-origin": "*",
    "content-type": "application/typescript; charset=utf-8",
    "referrer-policy": "strict-origin-when-cross-origin",
    "vary": "Accept-Encoding, Origin",
    "age": "24142501",
    "cross-origin-opener-policy": "same-origin",
    "cache-control": "public, max-age=31536000, immutable",
    "content-length": "6677",
    "server-timing": "fetchSource;dur=52",
    "x-frame-options": "DENY",
    "content-security-policy": "default-src 'none'; style-src 'unsafe-inline'; sandbox",
    "via": "http/2 edgeproxy-h",
    "x-amz-version-id": "NlDBdvFHSrEjxE9GKsOEoFgjHIrTcy.e"
  },
  "url": "https://deno.land/std@0.132.0/node/util.ts",
  "now": {
    "secs_since_epoch": 1728034552,
    "nanos_since_epoch": 539487474
  }
}